AUTHOR.txt
CHANGES.txt
COPYRIGHT.txt
LICENSE.txt
setup.py
src/falkolab/__init__.py
src/falkolab.ext3.direct.egg-info/PKG-INFO
src/falkolab.ext3.direct.egg-info/SOURCES.txt
src/falkolab.ext3.direct.egg-info/dependency_links.txt
src/falkolab.ext3.direct.egg-info/namespace_packages.txt
src/falkolab.ext3.direct.egg-info/not-zip-safe
src/falkolab.ext3.direct.egg-info/requires.txt
src/falkolab.ext3.direct.egg-info/top_level.txt
src/falkolab/ext3/__init__.py
src/falkolab/ext3/direct/CONFIG.txt
src/falkolab/ext3/direct/README.txt
src/falkolab/ext3/direct/ROUTER.txt
src/falkolab/ext3/direct/__init__.py
src/falkolab/ext3/direct/api.py
src/falkolab/ext3/direct/config.py
src/falkolab/ext3/direct/configure.zcml
src/falkolab/ext3/direct/decorator.py
src/falkolab/ext3/direct/directprovider.py
src/falkolab/ext3/direct/directrequest.py
src/falkolab/ext3/direct/directview.py
src/falkolab/ext3/direct/ftesting.zcml
src/falkolab/ext3/direct/ftests.py
src/falkolab/ext3/direct/interfaces.py
src/falkolab/ext3/direct/javascriptlink_viewlet.pt
src/falkolab/ext3/direct/jsonsupport.py
src/falkolab/ext3/direct/meta.zcml
src/falkolab/ext3/direct/metaconfigure.py
src/falkolab/ext3/direct/metadirectives.py
src/falkolab/ext3/direct/remotingprovider.py
src/falkolab/ext3/direct/router.py
src/falkolab/ext3/direct/testing.py
src/falkolab/ext3/direct/viewlet.py
src/falkolab/ext3/direct/publication/__init__.py
src/falkolab/ext3/direct/publication/configure.zcml
src/falkolab/ext3/direct/publication/interfaces.py
src/falkolab/ext3/direct/publication/publication.py
src/falkolab/ext3/direct/publication/request.py
src/falkolab/ext3/direct/publication/requestpublicationfactory.py
src/falkolab/ext3/direct/publication/response.py
src/falkolab/ext3/direct/tests/__init__.py
src/falkolab/ext3/direct/tests/test_functional.py